{
  "live_overview": {
    "当日开播场次数": "post_content_cnt_nd",
    "当日开播时长（分钟）": "post_time_nd",
    "当日观看人数": "look_uv_nd",
    "当日观看次数": "look_pv_nd",
    "当日新增粉丝数": "atn_uv_nd",
    "当日转粉率": "atn_uv_rate_nd",
    "当日粉丝回访率": "fans_return_rate_nd",
    "当日商品曝光人数": "expo_uv_itm_nd",
    "当日商品曝光次数": "expo_pv_itm_nd",
    "当日商品点击人数": "ipv_uv_nd",
    "当日商品点击次数": "ipv_nd",
    "当日新客成交人数": "pay_byr_cnt_nd_new",
    "当日新客成交金额": "pay_amt_nd_new",
    "观看总时长": "look_time_nd",
    "人均观看时长（秒）": "look_time_pu_nd",
    "次均观看时长（秒）": "look_time_pt_nd",
    "当日点赞人数": "fvr_uv_nd",
    "当日点赞次数": "fvr_pv_nd",
    "当日评论人数": "cmt_uv_nd",
    "当日评论次数": "cmt_pv_nd",
    "当日分享人数": "shr_uv_nd",
    "当日分享次数": "shr_pv_nd",
    "当日互动人数": "sns_uv_nd",
    "当日互动次数": "sns_pv_nd",
    "当日人均互动次数": "sns_pv_pu_nd",
    "当日加购人数": "cart_uv_nd",
    "当日加购次数": "cart_pv_nd",
    "当日加购件数": "cart_itm_qty_nd",
    "当日加购金额（元）": "cart_amt_nd",
    "当日成交人数": "pay_byr_cnt_nd",
    "当日成交转化率": "cvr_nd",
    "当日成交件数": "pay_itm_qty_nd",
    "当日成交笔数": "pay_ord_cnt_nd",
    "当日成交金额（元）": "pay_amt_nd",
    "当日确认收货人数": "confirm_byr_cnt_nd",
    "当日确认收货件数": "confirm_itm_qty_nd",
    "当日确认收货笔数": "confirm_ord_cnt_nd",
    "当日确认收货金额（元）": "confirm_amt_nd",
    "当日新零售成交人数": "payBuyerCnt1dO2o",
    "当日新零售成交（元）": "payAmt1dO2o",
    "当日客单价（元）": "atv_nd",
    "当日笔单价（元）": "aov_nd",
    "当日件单价（元）": "aiv_nd",
    "当日退款人数": "rfd_byr_cnt_nd_filter",
    "当日退款件数": "rfd_itm_qty_nd_filter",
    "当日退款笔数": "rfd_ord_cnt_nd_filter",
    "当日退款金额（元）": "rfd_amt_nd_filter",
    "直播间新增入会数": "mbr_cnt_incr_nd",
    "当日会员成交人数": "pay_byr_cnt_nd_mbr",
    "当日会员成交金额": "pay_amt_nd_mbr",
    "本店商品直播成交（含达播）": "pay_amt_nd_slr",
    "本店商品直播成交占比（含达播）": "pay_amt_nd_slr_rate",
    "会员成交件数": "pay_itm_qty_nd_mbr",
    "会员成交笔数": "pay_ord_cnt_nd_mbr",
    "本店商品自播成交": "pay_amt_nd_self",
    "本店商品自播成交占比": "pay_amt_nd_self_rate",
    "捧场购成交人数": "payBuyerCnt1dPcg",
    "捧场购成交笔数": "payOrderCnt1dPcg",
    "捧场购成交件数": "payItemQty1dPcg",
    "捧场购成交金额（元）": "payAmt1dPcg",
    "捧场购退款人数": "refundBuyerCnt1dPcg",
    "捧场购退款笔数": "refundOrderCnt1dPcg",
    "捧场购退款件数": "refundItemQty1dPcg",
    "捧场购退款金额（元）": "refundRealAmt1dPcg",
    "当日淘花花数": "bCoinCount",
    "当日充值打赏人数": "bCoinUv",
    "当日充值打赏礼物数": "bCoinCnt",
    "统计日期": "ds"
  }
}
